{
	"info": {
		"_postman_id": "a84dd3a9-5c3f-4c56-885a-643fbd97fd0e",
		"name": "API_NodeJs_Basico",
		"schema": "https://schema.getpostman.com/json/collection/v2.1.0/collection.json"
	},
	"item": [
		{
			"name": "Index",
			"item": [
				{
					"name": "Get na raiz",
					"request": {
						"method": "GET",
						"header": [
							{
								"key": "token",
								"value": "eyJhbGciOiJIUzI1NiIsInR5cCI6IkpXVCJ9.eyJpZCI6IjVmYzJkNTBlNDQyMGYwNjI1ODgwOWIxMSIsImlhdCI6MTYwNjYwNDA0NiwiZXhwIjoxNjA3MjA4ODQ2fQ.FfpuvioV9OdJPwtrpGybPZxSAB_SLrYAc9iaWsabj10",
								"type": "text"
							}
						],
						"url": {
							"raw": "http://localhost:3000",
							"protocol": "http",
							"host": [
								"localhost"
							],
							"port": "3000",
							"query": [
								{
									"key": "",
									"value": "1234",
									"disabled": true
								}
							]
						}
					},
					"response": []
				}
			],
			"protocolProfileBehavior": {}
		},
		{
			"name": "Users",
			"item": [
				{
					"name": "Get na rota de users",
					"request": {
						"method": "GET",
						"header": [],
						"url": {
							"raw": "http://localhost:3000/users",
							"protocol": "http",
							"host": [
								"localhost"
							],
							"port": "3000",
							"path": [
								"users"
							]
						}
					},
					"response": []
				},
				{
					"name": "POST na rota de users",
					"request": {
						"method": "POST",
						"header": [],
						"url": {
							"raw": "http://localhost:3000/users",
							"protocol": "http",
							"host": [
								"localhost"
							],
							"port": "3000",
							"path": [
								"users"
							]
						}
					},
					"response": []
				},
				{
					"name": "POST na rota de create users",
					"request": {
						"method": "POST",
						"header": [],
						"body": {
							"mode": "raw",
							"raw": "{\r\n    \"email\": \"testes6@email.com\",\r\n    \"password\": \"123456\"\r\n}",
							"options": {
								"raw": {
									"language": "json"
								}
							}
						},
						"url": {
							"raw": "http://localhost:3000/users/create",
							"protocol": "http",
							"host": [
								"localhost"
							],
							"port": "3000",
							"path": [
								"users",
								"create"
							]
						}
					},
					"response": []
				},
				{
					"name": "POST na rota de AUTH users",
					"request": {
						"method": "POST",
						"header": [],
						"body": {
							"mode": "raw",
							"raw": "{\r\n    \"email\" : \"testes4@email.com\",\r\n    \"password\" : \"123456\"\r\n}",
							"options": {
								"raw": {
									"language": "json"
								}
							}
						},
						"url": {
							"raw": "http://localhost:3000/users/auth",
							"protocol": "http",
							"host": [
								"localhost"
							],
							"port": "3000",
							"path": [
								"users",
								"auth"
							]
						}
					},
					"response": []
				}
			],
			"protocolProfileBehavior": {}
		}
	],
	"protocolProfileBehavior": {}
}